[
 {
  "distance": 25.5,
  "pos": "ADJ",
  "text": "strategic"
 },
 {
  "distance": 81.66666666666667,
  "pos": "ADJ",
  "text": "bright"
 },
 {
  "distance": 89.75,
  "pos": "ADJ",
  "text": "binding"
 },
 {
  "distance": 96.66666666666667,
  "pos": "ADJ",
  "text": "safer"
 },
 {
  "distance": 107.54545454545455,
  "pos": "ADJ",
  "text": "secure"
 },
 {
  "distance": 111,
  "pos": "ADJ",
  "text": "sophisticated"
 },
 {
  "distance": 111.45454545454545,
  "pos": "ADJ",
  "text": "final"
 },
 {
  "distance": 120.33333333333333,
  "pos": "ADJ",
  "text": "stable"
 },
 {
  "distance": 123,
  "pos": "ADJ",
  "text": "terrorist"
 },
 {
  "distance": 123.5,
  "pos": "ADJ",
  "text": "total"
 },
 {
  "distance": 114,
  "pos": "ADP",
  "text": "after"
 },
 {
  "distance": 119.41176470588235,
  "pos": "ADP",
  "text": "despite"
 },
 {
  "distance": 141.375,
  "pos": "ADP",
  "text": "inside"
 },
 {
  "distance": 153.14285714285714,
  "pos": "ADP",
  "text": "up"
 },
 {
  "distance": 156.75,
  "pos": "ADP",
  "text": "upon"
 },
 {
  "distance": 157,
  "pos": "ADP",
  "text": "so"
 },
 {
  "distance": 167.6,
  "pos": "ADP",
  "text": "though"
 },
 {
  "distance": 170.14285714285714,
  "pos": "ADP",
  "text": "across"
 },
 {
  "distance": 196.6153846153846,
  "pos": "ADP",
  "text": "toward"
 },
 {
  "distance": 199.5,
  "pos": "ADP",
  "text": "during"
 },
 {
  "distance": 25,
  "pos": "ADV",
  "text": "yet"
 },
 {
  "distance": 71,
  "pos": "ADV",
  "text": "nevertheless"
 },
 {
  "distance": 83.3157894736842,
  "pos": "ADV",
  "text": "legally"
 },
 {
  "distance": 84.25,
  "pos": "ADV",
  "text": "apparently"
 },
 {
  "distance": 96,
  "pos": "ADV",
  "text": "secondly"
 },
 {
  "distance": 102.33333333333333,
  "pos": "ADV",
  "text": "deep"
 },
 {
  "distance": 110.6470588235294,
  "pos": "ADV",
  "text": "too"
 },
 {
  "distance": 122.3125,
  "pos": "ADV",
  "text": "definitely"
 },
 {
  "distance": 125,
  "pos": "ADV",
  "text": "finally"
 },
 {
  "distance": 129.1,
  "pos": "ADV",
  "text": "sooner"
 },
 {
  "distance": 224.5,
  "pos": "CONJ",
  "text": "and"
 },
 {
  "distance": 283.23664122137404,
  "pos": "CONJ",
  "text": "but"
 },
 {
  "distance": 349.47058823529414,
  "pos": "CONJ",
  "text": "either"
 },
 {
  "distance": 387.5,
  "pos": "CONJ",
  "text": "both"
 },
 {
  "distance": 57.666666666666664,
  "pos": "DET",
  "text": "te"
 },
 {
  "distance": 162.75,
  "pos": "DET",
  "text": "such"
 },
 {
  "distance": 175,
  "pos": "DET",
  "text": "whatever"
 },
 {
  "distance": 185.5,
  "pos": "DET",
  "text": "some"
 },
 {
  "distance": 191.44444444444446,
  "pos": "DET",
  "text": "there"
 },
 {
  "distance": 216.425,
  "pos": "DET",
  "text": "any"
 },
 {
  "distance": 227,
  "pos": "DET",
  "text": "both"
 },
 {
  "distance": 227.8235294117647,
  "pos": "DET",
  "text": "each"
 },
 {
  "distance": 229.0909090909091,
  "pos": "DET",
  "text": "all"
 },
 {
  "distance": 255.85714285714286,
  "pos": "DET",
  "text": "that"
 },
 {
  "distance": 21.666666666666668,
  "pos": "NOUN",
  "text": "dandong"
 },
 {
  "distance": 22,
  "pos": "NOUN",
  "text": "hongxiang"
 },
 {
  "distance": 22.333333333333332,
  "pos": "NOUN",
  "text": "equipment"
 },
 {
  "distance": 22.666666666666668,
  "pos": "NOUN",
  "text": "development"
 },
 {
  "distance": 23,
  "pos": "NOUN",
  "text": "co."
 },
 {
  "distance": 23.333333333333332,
  "pos": "NOUN",
  "text": "ltd"
 },
 {
  "distance": 24.333333333333332,
  "pos": "NOUN",
  "text": "fine"
 },
 {
  "distance": 26.333333333333332,
  "pos": "NOUN",
  "text": "zte"
 },
 {
  "distance": 27,
  "pos": "NOUN",
  "text": "tech"
 },
 {
  "distance": 39.666666666666664,
  "pos": "NOUN",
  "text": "assad"
 },
 {
  "distance": 67,
  "pos": "NUM",
  "text": "19.03."
 },
 {
  "distance": 87.5,
  "pos": "NUM",
  "text": "1945"
 },
 {
  "distance": 121.16666666666667,
  "pos": "NUM",
  "text": "$1.2"
 },
 {
  "distance": 125.14285714285714,
  "pos": "NUM",
  "text": "30"
 },
 {
  "distance": 143.5,
  "pos": "NUM",
  "text": "35"
 },
 {
  "distance": 147.5,
  "pos": "NUM",
  "text": "113"
 },
 {
  "distance": 147.52,
  "pos": "NUM",
  "text": "billion"
 },
 {
  "distance": 147.75,
  "pos": "NUM",
  "text": "4"
 },
 {
  "distance": 155.25,
  "pos": "NUM",
  "text": "200"
 },
 {
  "distance": 156.83333333333334,
  "pos": "NUM",
  "text": "21"
 },
 {
  "distance": 116.75,
  "pos": "PRON",
  "text": "she"
 },
 {
  "distance": 155,
  "pos": "PRON",
  "text": "his"
 },
 {
  "distance": 171.31428571428572,
  "pos": "PRON",
  "text": "you"
 },
 {
  "distance": 220.33333333333334,
  "pos": "PRON",
  "text": "what"
 },
 {
  "distance": 232.83333333333334,
  "pos": "PRON",
  "text": "himself"
 },
 {
  "distance": 247.87179487179486,
  "pos": "PRON",
  "text": "it"
 },
 {
  "distance": 249.89473684210526,
  "pos": "PRON",
  "text": "me"
 },
 {
  "distance": 252.9391304347826,
  "pos": "PRON",
  "text": "i"
 },
 {
  "distance": 253,
  "pos": "PRON",
  "text": "her"
 },
 {
  "distance": 256.5681818181818,
  "pos": "PRON",
  "text": "they"
 },
 {
  "distance": 188.25,
  "pos": "PRT",
  "text": "off"
 },
 {
  "distance": 207.3,
  "pos": "PRT",
  "text": "in"
 },
 {
  "distance": 210.69811320754718,
  "pos": "PRT",
  "text": "'"
 },
 {
  "distance": 225.77777777777777,
  "pos": "PRT",
  "text": "on"
 },
 {
  "distance": 230.08823529411765,
  "pos": "PRT",
  "text": "back"
 },
 {
  "distance": 254,
  "pos": "PRT",
  "text": "away"
 },
 {
  "distance": 268.3246753246753,
  "pos": "PRT",
  "text": "up"
 },
 {
  "distance": 283.160751565762,
  "pos": "PRT",
  "text": "'s"
 },
 {
  "distance": 291.68674698795184,
  "pos": "PRT",
  "text": "out"
 },
 {
  "distance": 341.5,
  "pos": "PRT",
  "text": "through"
 },
 {
  "distance": 22.666666666666668,
  "pos": "VERB",
  "text": "selling"
 },
 {
  "distance": 37.07142857142857,
  "pos": "VERB",
  "text": "supported"
 },
 {
  "distance": 46.333333333333336,
  "pos": "VERB",
  "text": "sanctioning"
 },
 {
  "distance": 47,
  "pos": "VERB",
  "text": "fanned"
 },
 {
  "distance": 47,
  "pos": "VERB",
  "text": "authorised"
 },
 {
  "distance": 48.125,
  "pos": "VERB",
  "text": "engaging"
 },
 {
  "distance": 50.333333333333336,
  "pos": "VERB",
  "text": "dipped"
 },
 {
  "distance": 50.5,
  "pos": "VERB",
  "text": "tested"
 },
 {
  "distance": 50.666666666666664,
  "pos": "VERB",
  "text": "unsealed"
 },
 {
  "distance": 54,
  "pos": "VERB",
  "text": "ignored"
 }
]